TracNumberedHeadlinesPlugin-0.5.dist-info/METADATA
TracNumberedHeadlinesPlugin-0.5.dist-info/RECORD
TracNumberedHeadlinesPlugin-0.5.dist-info/WHEEL
TracNumberedHeadlinesPlugin-0.5.dist-info/entry_points.txt
TracNumberedHeadlinesPlugin-0.5.dist-info/top_level.txt
tracnumberedheadlines/__init__.py
tracnumberedheadlines/plugin.py
