Metadata-Version: 2.1
Name: TracNumberedHeadlinesPlugin
Version: 0.5
Summary: Trac Plug-in to add numbered headlines.
Home-page: http://www.trac-hacks.org/wiki/NumberedHeadlinesPlugin
Author: Martin Scharrer
Author-email: martin@scharrer-online.de
License: GPLv3
Keywords: trac numbered headlines plugin
Platform: UNKNOWN
Classifier: Framework :: Trac
